kafkashell/__init__.py
kafkashell/bindings.py
kafkashell/completer.py
kafkashell/config.py
kafkashell/constants.py
kafkashell/executor.py
kafkashell/helpers.py
kafkashell/main.py
kafkashell/settings.py
kafkashell/style.py
kafkashell/toolbar.py
kafkashell/version.py
kafkashell/data/completer-acks.json
kafkashell/data/completer-acks.schema
kafkashell/data/completer-booleans.json
kafkashell/data/completer-booleans.schema
kafkashell/data/completer-cleanup-policy.json
kafkashell/data/completer-cleanup-policy.schema
kafkashell/data/completer-compression-codecs.json
kafkashell/data/completer-compression-codecs.schema
kafkashell/data/completer-entity-types.json
kafkashell/data/completer-entity-types.schema
kafkashell/data/completer-kafka-configs.json
kafkashell/data/completer-kafka-configs.schema
kafkashell/data/completer-ksql-output.json
kafkashell/data/completer-ksql-output.schema
kafkashell/data/completer-reset-policies.json
kafkashell/data/completer-reset-policies.schema
kafkashell/data/completer-resource-pattern-types.json
kafkashell/data/completer-resource-pattern-types.schema
kafkashell/data/completer-timestamp-types.json
kafkashell/data/completer-timestamp-types.schema
kafkashell/data/completer.json
kafkashell/data/completer.schema
kafkashell/data/shell-config.schema
kafkashell/data/shell-config.yaml
kafka_shell-0.1.4.dist-info/LICENSE
kafka_shell-0.1.4.dist-info/METADATA
kafka_shell-0.1.4.dist-info/WHEEL
kafka_shell-0.1.4.dist-info/entry_points.txt
kafka_shell-0.1.4.dist-info/top_level.txt
kafka_shell-0.1.4.dist-info/RECORD
