Metadata-Version: 2.1
Name: kafka-shell
Version: 0.1.4
Summary: A supercharged, interactive Kafka shell built on top of the existing Kafka CLI tools.
Home-page: https://github.com/devshawn/kafka-shell
Author: Shawn Seymour
Author-email: shawn@devshawn.com
License: Apache License 2.0
Keywords: kafka,shell,prompt,apache,autocomplete,streams,cli
Platform: UNKNOWN
Classifier: Development Status :: 4 - Beta
Classifier: Intended Audience :: Developers
Classifier: Intended Audience :: System Administrators
Classifier: License :: OSI Approved :: Apache Software License
Classifier: Natural Language :: English
Classifier: Operating System :: MacOS
Classifier: Operating System :: Unix
Classifier: Programming Language :: Python :: 2
Classifier: Programming Language :: Python :: 2.7
Classifier: Programming Language :: Python :: 3
Classifier: Programming Language :: Python :: 3.5
Classifier: Programming Language :: Python :: 3.6
Classifier: Programming Language :: Python :: 3.7
Classifier: Topic :: Software Development
Classifier: Topic :: Software Development :: Libraries :: Python Modules
Requires-Dist: prompt-toolkit (>=2.0.9)
Requires-Dist: pygments (<3.0.0,>=2.1.3)
Requires-Dist: fuzzyfinder (>=2.0.0)
Requires-Dist: jsonschema (>=3.0.1)
Requires-Dist: oyaml (>=0.8)
